weave/__about__.py
weave/__init__.py
weave/dimension.py
weave/distance.py
weave/kernels.py
weave/smoother.py
weave/utils.py
weighted_average-1.3.0.dist-info/LICENSE
weighted_average-1.3.0.dist-info/METADATA
weighted_average-1.3.0.dist-info/WHEEL
weighted_average-1.3.0.dist-info/top_level.txt
weighted_average-1.3.0.dist-info/RECORD
