Metadata-Version: 2.1
Name: weighted-average
Version: 1.3.0
Summary: Smooth data across multiple dimensions using weighted averages
Home-page: https://github.com/ihmeuw-msca/weighted-average
Author: IHME Math Sciences
Author-email: ihme.math.sciences@gmail.com
License: BSD 2-Clause License
Classifier: License :: OSI Approved :: BSD License
Classifier: Intended Audience :: Developers
Classifier: Intended Audience :: Science/Research
Classifier: Natural Language :: English
Classifier: Programming Language :: Python :: 3
License-File: LICENSE
Requires-Dist: numba
Requires-Dist: numpy
Requires-Dist: pandas
Requires-Dist: scipy
Provides-Extra: dev
Requires-Dist: hypothesis ; extra == 'dev'
Requires-Dist: pytest ; extra == 'dev'
Provides-Extra: doc
Requires-Dist: furo ; extra == 'doc'
Requires-Dist: sphinx ; extra == 'doc'
Requires-Dist: sphinx-autodoc-typehints ; extra == 'doc'
